openstb/simulator/__init__.py
openstb/simulator/__main__.py
openstb/simulator/py.typed
openstb/simulator/types.py
openstb/simulator/util.py
openstb/simulator/cli/__init__.py
openstb/simulator/cli/log.py
openstb/simulator/cli/run.py
openstb/simulator/cluster/__init__.py
openstb/simulator/cluster/dask_local.py
openstb/simulator/cluster/dask_mpi.py
openstb/simulator/config_loader/__init__.py
openstb/simulator/config_loader/toml.py
openstb/simulator/distortion/__init__.py
openstb/simulator/distortion/beampattern.py
openstb/simulator/distortion/doppler.py
openstb/simulator/distortion/environmental.py
openstb/simulator/environment/__init__.py
openstb/simulator/environment/invariant.py
openstb/simulator/plugin/__init__.py
openstb/simulator/plugin/abc.py
openstb/simulator/plugin/loader.py
openstb/simulator/plugin/util.py
openstb/simulator/result_converter/__init__.py
openstb/simulator/result_converter/matlab.py
openstb/simulator/result_converter/numpy.py
openstb/simulator/simulation/__init__.py
openstb/simulator/simulation/points.py
openstb/simulator/system/__init__.py
openstb/simulator/system/ping_times.py
openstb/simulator/system/signal.py
openstb/simulator/system/signal_windows.py
openstb/simulator/system/trajectory.py
openstb/simulator/system/transducer.py
openstb/simulator/target/__init__.py
openstb/simulator/target/points.py
openstb/simulator/travel_time/__init__.py
openstb/simulator/travel_time/iterative.py
openstb/simulator/travel_time/stop_and_hop.py
openstb_simulator-0.6.1.dist-info/METADATA
openstb_simulator-0.6.1.dist-info/WHEEL
openstb_simulator-0.6.1.dist-info/entry_points.txt
openstb_simulator-0.6.1.dist-info/RECORD
