Metadata-Version: 2.4
Name: openstb-simulator
Version: 0.6.1
Summary: SONAR simulator
Project-URL: Homepage, https://openstb.dev
Project-URL: Documentation, https://docs.openstb.dev
Project-URL: Repository, https://github.com/openstb/simulator.git
Project-URL: Issues, https://github.com/openstb/simulator/issues
Requires-Python: >=3.11
Requires-Dist: click
Requires-Dist: cryptography
Requires-Dist: dask[distributed]
Requires-Dist: numpy
Requires-Dist: openstb-i18n
Requires-Dist: quaternionic
Requires-Dist: rich
Requires-Dist: scipy
Requires-Dist: zarr<4,>=3
Provides-Extra: dask-diagnostics
Requires-Dist: dask[diagnostics]; extra == 'dask-diagnostics'
Provides-Extra: dev
Requires-Dist: dask[diagnostics]; extra == 'dev'
Requires-Dist: mkdocs; extra == 'dev'
Requires-Dist: mkdocs-api-autonav; extra == 'dev'
Requires-Dist: mkdocs-material; extra == 'dev'
Requires-Dist: mkdocstrings[python]; extra == 'dev'
Requires-Dist: mypy; extra == 'dev'
Requires-Dist: pytest; extra == 'dev'
Requires-Dist: pytest-cov; extra == 'dev'
Requires-Dist: requests; extra == 'dev'
Requires-Dist: ruff; extra == 'dev'
Provides-Extra: doc
Requires-Dist: mkdocs; extra == 'doc'
Requires-Dist: mkdocs-api-autonav; extra == 'doc'
Requires-Dist: mkdocs-material; extra == 'doc'
Requires-Dist: mkdocstrings[python]; extra == 'doc'
Provides-Extra: mpi
Requires-Dist: dask-mpi; extra == 'mpi'
Requires-Dist: mpi4py; extra == 'mpi'
Provides-Extra: tests
Requires-Dist: pytest; extra == 'tests'
Requires-Dist: pytest-cov; extra == 'tests'
Requires-Dist: requests; extra == 'tests'
